hget/__init__.py
hget/_version.py
hget/ftp.py
hget/main.py
hget/src.py
hget/utils.py
hget-1.0.6.dist-info/LICENSE
hget-1.0.6.dist-info/METADATA
hget-1.0.6.dist-info/WHEEL
hget-1.0.6.dist-info/entry_points.txt
hget-1.0.6.dist-info/top_level.txt
hget-1.0.6.dist-info/RECORD
