Metadata-Version: 2.1
Name: hget
Version: 1.0.6
Summary: UNKNOWN
Home-page: https://github.com/yodeng/hget
License: MIT
Platform: UNKNOWN
Requires-Python: >=3.8
Requires-Dist: Cython
Requires-Dist: requests
Requires-Dist: aiohttp
Requires-Dist: boto3
Requires-Dist: joblib
Requires-Dist: tqdm
